nostalgia_fitbit/__init__.py
nostalgia_fitbit/__main__.py
nostalgia_fitbit/_version.py
nostalgia_fitbit/auth.py
nostalgia_fitbit/client.py
nostalgia_fitbit/datastore.py
nostalgia_fitbit/export.py
nostalgia_fitbit/report.py
nostalgia_fitbit/sync.py
nostalgia_fitbit/static/chart.js
nostalgia_fitbit/static/report.css
nostalgia_fitbit-0.6.0.dist-info/LICENSE
nostalgia_fitbit-0.6.0.dist-info/METADATA
nostalgia_fitbit-0.6.0.dist-info/WHEEL
nostalgia_fitbit-0.6.0.dist-info/entry_points.txt
nostalgia_fitbit-0.6.0.dist-info/top_level.txt
nostalgia_fitbit-0.6.0.dist-info/RECORD
