Metadata-Version: 2.1
Name: nostalgia-fitbit
Version: 0.6.0
Summary: export fitbit data
Home-page: http://github.com/nostalgia-dev/nostalgia_fitbit/
Author: Pascal van Kooten
Author-email: pascal@vks.ai
License: LICENSE.txt
Keywords: fitbit data export json
Platform: UNKNOWN
Classifier: Environment :: Console
Classifier: Intended Audience :: Developers
Classifier: Intended Audience :: Healthcare Industry
Classifier: License :: OSI Approved :: GNU General Public License v3 (GPLv3)
Classifier: Operating System :: OS Independent
Classifier: Programming Language :: Python :: 3
Classifier: Programming Language :: Python :: 3.3
Classifier: Programming Language :: Python :: 3.4
Classifier: Programming Language :: Python :: 3.5
Classifier: Programming Language :: Python :: 3.6
Classifier: Programming Language :: Python :: 3.7
Classifier: Programming Language :: Python :: Implementation :: PyPy
Classifier: Programming Language :: Python
Classifier: Topic :: Scientific/Engineering :: Medical Science Apps.
Classifier: Topic :: Scientific/Engineering :: Visualization
Classifier: Topic :: Software Development :: Libraries :: Python Modules
Classifier: Topic :: System :: Archiving
Classifier: Topic :: Utilities
Requires-Dist: requests
Requires-Dist: dominate
Requires-Dist: just
Requires-Dist: python-dateutil
